LICENSE
README.md
setup.py
citation_crawler/__init__.py
citation_crawler/__main__.py
citation_crawler/arg.py
citation_crawler/graph.py
citation_crawler/items.py
citation_crawler.egg-info/PKG-INFO
citation_crawler.egg-info/SOURCES.txt
citation_crawler.egg-info/dependency_links.txt
citation_crawler.egg-info/requires.txt
citation_crawler.egg-info/top_level.txt
citation_crawler/crawlers/__init__.py
citation_crawler/crawlers/common.py
citation_crawler/crawlers/ss.py
citation_crawler/init/__init__.py
citation_crawler/init/neo4j.py
citation_crawler/summarizers/__init__.py
citation_crawler/summarizers/neo4j.py
citation_crawler/summarizers/nx.py