Metadata-Version: 2.1
Name: citation-crawler
Version: 2.9.3
Summary: Asynchronous high-concurrency citation crawler, use with caution!
Home-page: https://github.com/yindaheng98/citation-crawler
Author: yindaheng98
Author-email: yindaheng98@gmail.com
License: UNKNOWN
Platform: UNKNOWN
Classifier: Programming Language :: Python :: 3
Classifier: License :: OSI Approved :: MIT License
Classifier: Operating System :: OS Independent
License-File: LICENSE
